letter_algo.py
letter_algo-1.0.3.dist-info/LICENSE
letter_algo-1.0.3.dist-info/WHEEL
letter_algo-1.0.3.dist-info/METADATA
letter_algo-1.0.3.dist-info/RECORD
